<annotation>
	<folder>test</folder>
	<filename>21605030994.73.jpeg</filename>
	<path>/home/student/CarND-Capstone-Project/ros/src/tl_detector/test/21605030994.73.jpeg</path>
	<source>
		<database>Unknown</database>
	</source>
	<size>
		<width>800</width>
		<height>600</height>
		<depth>3</depth>
	</size>
	<segmented>0</segmented>
	<object>
		<name>green</name>
		<pose>Unspecified</pose>
		<truncated>0</truncated>
		<difficult>0</difficult>
		<bndbox>
			<xmin>184</xmin>
			<ymin>411</ymin>
			<xmax>216</xmax>
			<ymax>481</ymax>
		</bndbox>
	</object>
	<object>
		<name>green</name>
		<pose>Unspecified</pose>
		<truncated>0</truncated>
		<difficult>0</difficult>
		<bndbox>
			<xmin>325</xmin>
			<ymin>414</ymin>
			<xmax>360</xmax>
			<ymax>485</ymax>
		</bndbox>
	</object>
	<object>
		<name>green</name>
		<pose>Unspecified</pose>
		<truncated>0</truncated>
		<difficult>0</difficult>
		<bndbox>
			<xmin>466</xmin>
			<ymin>414</ymin>
			<xmax>500</xmax>
			<ymax>488</ymax>
		</bndbox>
	</object>
</annotation>
